becca_toolbox/LICENSE
becca_toolbox/__init__.py
becca_toolbox/feature_tools.py
becca_toolbox/ffmpeg_tools.py
becca_toolbox-0.10.1.dist-info/METADATA
becca_toolbox-0.10.1.dist-info/RECORD
becca_toolbox-0.10.1.dist-info/WHEEL
becca_toolbox-0.10.1.dist-info/top_level.txt
