Metadata-Version: 2.1
Name: becca-toolbox
Version: 0.10.1
Summary: Some tools for working with Becca
Home-page: http://github.com/brohrer/becca_toolbox
Author: Brandon Rohrer
Author-email: brohrer@gmail.com
License: MIT
Download-URL: https://github.com/brohrer/becca_toolbox/archive/master.zip
Platform: UNKNOWN
